fasttext_pybind.cpython-39-i386-linux-gnu.so
fasttext_predict-0.9.2.3.dist-info/top_level.txt
fasttext_predict-0.9.2.3.dist-info/RECORD
fasttext_predict-0.9.2.3.dist-info/LICENSE
fasttext_predict-0.9.2.3.dist-info/METADATA
fasttext_predict-0.9.2.3.dist-info/WHEEL
fasttext_predict.libs/libgcc_s-8b50eaaa.so.1
fasttext_predict.libs/libstdc++-8baf04f9.so.6.0.28
fasttext/FastText.py
fasttext/__init__.py
