Metadata-Version: 2.1
Name: fasttext-predict
Version: 0.9.2.3
Summary: fasttext with wheels and no external dependency, but only the predict method (<1MB)
Home-page: https://github.com/searxng/fasttext-predict/
Author: Alexandre Flament
Author-email: alex.andre@al-f.net
License: MIT
Keywords: fasttext,language detection,language identification
Classifier: Development Status :: 3 - Alpha
Classifier: Intended Audience :: Developers
Classifier: Intended Audience :: Science/Research
Classifier: License :: OSI Approved :: MIT License
Classifier: Programming Language :: Python :: 3.9
Classifier: Programming Language :: Python :: 3.10
Classifier: Programming Language :: Python :: 3.11
Classifier: Programming Language :: Python :: 3.12
Classifier: Programming Language :: Python :: 3.13
Classifier: Topic :: Software Development
Classifier: Topic :: Scientific/Engineering
Classifier: Operating System :: Microsoft :: Windows
Classifier: Operating System :: POSIX
Classifier: Operating System :: Unix
Classifier: Operating System :: MacOS
License-File: LICENSE
